{
  "DataList": [
    {
      "EventContentId": 815,
      "DevName": "여름2부",
      "MapDifficulty": 1,
      "StepIndex": 0,
      "ConquestMap": "ConquestMap_Normal_815",
      "StepEnterScenarioGroupId": 10013020,
      "StepOpenConditionType": [],
      "StepOpenConditionParameter": [],
      "MapGoalLocalize": "UI_CONQUESTLOBBY_GOAL_STEP4",
      "StepGoalLocalize": "UI_CONQUESTLOBBY_GOAL_STEP1",
      "StepNameLocalize": "",
      "ConquestMapBG": "Conquest_Back_01_Normal",
      "CameraSettingId": 81501
    },
    {
      "EventContentId": 815,
      "DevName": "여름2부",
      "MapDifficulty": 1,
      "StepIndex": 1,
      "ConquestMap": "ConquestMap_Normal_815",
      "StepEnterScenarioGroupId": 10013040,
      "StepOpenConditionType": [
        2,
        4
      ],
      "StepOpenConditionParameter": [
        "Item;80134;1",
        "81511121"
      ],
      "MapGoalLocalize": "UI_CONQUESTLOBBY_GOAL_STEP4",
      "StepGoalLocalize": "UI_CONQUESTLOBBY_GOAL_STEP2",
      "StepNameLocalize": "",
      "ConquestMapBG": "Conquest_Back_01_Normal",
      "CameraSettingId": 81502
    },
    {
      "EventContentId": 815,
      "DevName": "여름2부",
      "MapDifficulty": 1,
      "StepIndex": 2,
      "ConquestMap": "ConquestMap_Normal_815",
      "StepEnterScenarioGroupId": 0,
      "StepOpenConditionType": [
        2,
        4
      ],
      "StepOpenConditionParameter": [
        "Item;80135;1",
        "81521131"
      ],
      "MapGoalLocalize": "UI_CONQUESTLOBBY_GOAL_STEP4",
      "StepGoalLocalize": "UI_CONQUESTLOBBY_GOAL_STEP3",
      "StepNameLocalize": "",
      "ConquestMapBG": "Conquest_Back_01_Normal",
      "CameraSettingId": 81503
    },
    {
      "EventContentId": 815,
      "DevName": "여름2부",
      "MapDifficulty": 1,
      "StepIndex": 3,
      "ConquestMap": "ConquestMap_Normal_815",
      "StepEnterScenarioGroupId": 10013070,
      "StepOpenConditionType": [
        2,
        4
      ],
      "StepOpenConditionParameter": [
        "Item;80136;1",
        "81531131"
      ],
      "MapGoalLocalize": "UI_CONQUESTLOBBY_GOAL_STEP4",
      "StepGoalLocalize": "UI_CONQUESTLOBBY_GOAL_STEP4",
      "StepNameLocalize": "",
      "ConquestMapBG": "Conquest_Back_01_Normal",
      "CameraSettingId": 81504
    },
    {
      "EventContentId": 815,
      "DevName": "여름2부",
      "MapDifficulty": 3,
      "StepIndex": 0,
      "ConquestMap": "ConquestMap_Challenge_815",
      "StepEnterScenarioGroupId": 0,
      "StepOpenConditionType": [
        1
      ],
      "StepOpenConditionParameter": [
        "1"
      ],
      "MapGoalLocalize": "UI_CONQUESTLOBBY_GOAL_CHALLENGE",
      "StepGoalLocalize": "UI_CONQUESTLOBBY_GOAL_CHALLENGE",
      "StepNameLocalize": "",
      "ConquestMapBG": "Conquest_Back_01_Challenge",
      "CameraSettingId": 81511
    },
    {
      "EventContentId": 822,
      "DevName": "최종장방주",
      "MapDifficulty": 1,
      "StepIndex": 0,
      "ConquestMap": "ConquestMap_Normal_822_1",
      "StepEnterScenarioGroupId": 0,
      "StepOpenConditionType": [],
      "StepOpenConditionParameter": [],
      "MapGoalLocalize": "UI_CONQUESTLOBBY_GOAL_STEP4",
      "StepGoalLocalize": "UI_CONQUESTLOBBY_GOAL_STEP1",
      "StepNameLocalize": "Stepname_EVENT_822_Normal_Step1",
      "ConquestMapBG": "Conquest_Back_02_Normal_Outer",
      "CameraSettingId": 82201
    },
    {
      "EventContentId": 822,
      "DevName": "최종장방주",
      "MapDifficulty": 1,
      "StepIndex": 1,
      "ConquestMap": "ConquestMap_Normal_822_2",
      "StepEnterScenarioGroupId": 0,
      "StepOpenConditionType": [
        2,
        4
      ],
      "StepOpenConditionParameter": [
        "Item;80203;1",
        "82211121"
      ],
      "MapGoalLocalize": "UI_CONQUESTLOBBY_GOAL_STEP4",
      "StepGoalLocalize": "UI_CONQUESTLOBBY_GOAL_STEP2",
      "StepNameLocalize": "Stepname_EVENT_822_Normal_Step2",
      "ConquestMapBG": "Conquest_Back_02_Normal_Outer",
      "CameraSettingId": 82202
    },
    {
      "EventContentId": 822,
      "DevName": "최종장방주",
      "MapDifficulty": 1,
      "StepIndex": 2,
      "ConquestMap": "ConquestMap_Normal_822_3",
      "StepEnterScenarioGroupId": 0,
      "StepOpenConditionType": [
        2,
        4
      ],
      "StepOpenConditionParameter": [
        "Item;80204;1",
        "82221131"
      ],
      "MapGoalLocalize": "UI_CONQUESTLOBBY_GOAL_STEP4",
      "StepGoalLocalize": "UI_CONQUESTLOBBY_GOAL_STEP3",
      "StepNameLocalize": "Stepname_EVENT_822_Normal_Step3",
      "ConquestMapBG": "Conquest_Back_02_Normal_Outer",
      "CameraSettingId": 82203
    },
    {
      "EventContentId": 822,
      "DevName": "최종장방주",
      "MapDifficulty": 1,
      "StepIndex": 3,
      "ConquestMap": "ConquestMap_Normal_822_4",
      "StepEnterScenarioGroupId": 0,
      "StepOpenConditionType": [
        2,
        4
      ],
      "StepOpenConditionParameter": [
        "Item;80205;1",
        "82231131"
      ],
      "MapGoalLocalize": "UI_CONQUESTLOBBY_GOAL_STEP4",
      "StepGoalLocalize": "UI_CONQUESTLOBBY_GOAL_STEP4",
      "StepNameLocalize": "Stepname_EVENT_822_Normal_Step4",
      "ConquestMapBG": "Conquest_Back_02_Normal_Inner",
      "CameraSettingId": 82204
    },
    {
      "EventContentId": 822,
      "DevName": "최종장방주",
      "MapDifficulty": 3,
      "StepIndex": 0,
      "ConquestMap": "ConquestMap_Challenge_822",
      "StepEnterScenarioGroupId": 0,
      "StepOpenConditionType": [
        1
      ],
      "StepOpenConditionParameter": [
        "1"
      ],
      "MapGoalLocalize": "UI_CONQUESTLOBBY_GOAL_CHALLENGE",
      "StepGoalLocalize": "UI_CONQUESTLOBBY_GOAL_CHALLENGE",
      "StepNameLocalize": "Stepname_EVENT_822_Challenge_Step0",
      "ConquestMapBG": "Conquest_Back_02_Normal_Inner",
      "CameraSettingId": 82211
    },
    {
      "EventContentId": 10815,
      "DevName": "여름2부",
      "MapDifficulty": 1,
      "StepIndex": 0,
      "ConquestMap": "ConquestMap_Normal_815",
      "StepEnterScenarioGroupId": 10013020,
      "StepOpenConditionType": [],
      "StepOpenConditionParameter": [],
      "MapGoalLocalize": "UI_CONQUESTLOBBY_GOAL_STEP4",
      "StepGoalLocalize": "UI_CONQUESTLOBBY_GOAL_STEP1",
      "StepNameLocalize": "",
      "ConquestMapBG": "Conquest_Back_01_Normal",
      "CameraSettingId": 81501
    },
    {
      "EventContentId": 10815,
      "DevName": "여름2부",
      "MapDifficulty": 1,
      "StepIndex": 1,
      "ConquestMap": "ConquestMap_Normal_815",
      "StepEnterScenarioGroupId": 10013040,
      "StepOpenConditionType": [
        2,
        4
      ],
      "StepOpenConditionParameter": [
        "Item;85134;1",
        "81511121"
      ],
      "MapGoalLocalize": "UI_CONQUESTLOBBY_GOAL_STEP4",
      "StepGoalLocalize": "UI_CONQUESTLOBBY_GOAL_STEP2",
      "StepNameLocalize": "",
      "ConquestMapBG": "Conquest_Back_01_Normal",
      "CameraSettingId": 81502
    },
    {
      "EventContentId": 10815,
      "DevName": "여름2부",
      "MapDifficulty": 1,
      "StepIndex": 2,
      "ConquestMap": "ConquestMap_Normal_815",
      "StepEnterScenarioGroupId": 0,
      "StepOpenConditionType": [
        2,
        4
      ],
      "StepOpenConditionParameter": [
        "Item;85135;1",
        "81521131"
      ],
      "MapGoalLocalize": "UI_CONQUESTLOBBY_GOAL_STEP4",
      "StepGoalLocalize": "UI_CONQUESTLOBBY_GOAL_STEP3",
      "StepNameLocalize": "",
      "ConquestMapBG": "Conquest_Back_01_Normal",
      "CameraSettingId": 81503
    },
    {
      "EventContentId": 10815,
      "DevName": "여름2부",
      "MapDifficulty": 1,
      "StepIndex": 3,
      "ConquestMap": "ConquestMap_Normal_815",
      "StepEnterScenarioGroupId": 10013070,
      "StepOpenConditionType": [
        2,
        4
      ],
      "StepOpenConditionParameter": [
        "Item;85136;1",
        "81531131"
      ],
      "MapGoalLocalize": "UI_CONQUESTLOBBY_GOAL_STEP4",
      "StepGoalLocalize": "UI_CONQUESTLOBBY_GOAL_STEP4",
      "StepNameLocalize": "",
      "ConquestMapBG": "Conquest_Back_01_Normal",
      "CameraSettingId": 81504
    },
    {
      "EventContentId": 10815,
      "DevName": "여름2부",
      "MapDifficulty": 3,
      "StepIndex": 0,
      "ConquestMap": "ConquestMap_Challenge_815",
      "StepEnterScenarioGroupId": 0,
      "StepOpenConditionType": [
        1
      ],
      "StepOpenConditionParameter": [
        "1"
      ],
      "MapGoalLocalize": "UI_CONQUESTLOBBY_GOAL_CHALLENGE",
      "StepGoalLocalize": "UI_CONQUESTLOBBY_GOAL_CHALLENGE",
      "StepNameLocalize": "",
      "ConquestMapBG": "Conquest_Back_01_Challenge",
      "CameraSettingId": 81511
    },
    {
      "EventContentId": 50822,
      "DevName": "최종장방주_메인스토리",
      "MapDifficulty": 1,
      "StepIndex": 0,
      "ConquestMap": "ConquestMap_Normal_822_1",
      "StepEnterScenarioGroupId": 0,
      "StepOpenConditionType": [],
      "StepOpenConditionParameter": [],
      "MapGoalLocalize": "UI_CONQUESTLOBBY_GOAL_STEP4",
      "StepGoalLocalize": "UI_CONQUESTLOBBY_GOAL_STEP1",
      "StepNameLocalize": "Stepname_EVENT_822_Normal_Step1",
      "ConquestMapBG": "Conquest_Back_02_Normal_Outer",
      "CameraSettingId": 82201
    },
    {
      "EventContentId": 50822,
      "DevName": "최종장방주_메인스토리",
      "MapDifficulty": 1,
      "StepIndex": 1,
      "ConquestMap": "ConquestMap_Normal_822_2",
      "StepEnterScenarioGroupId": 0,
      "StepOpenConditionType": [
        4
      ],
      "StepOpenConditionParameter": [
        "82211121"
      ],
      "MapGoalLocalize": "UI_CONQUESTLOBBY_GOAL_STEP4",
      "StepGoalLocalize": "UI_CONQUESTLOBBY_GOAL_STEP2",
      "StepNameLocalize": "Stepname_EVENT_822_Normal_Step2",
      "ConquestMapBG": "Conquest_Back_02_Normal_Outer",
      "CameraSettingId": 82202
    },
    {
      "EventContentId": 50822,
      "DevName": "최종장방주_메인스토리",
      "MapDifficulty": 1,
      "StepIndex": 2,
      "ConquestMap": "ConquestMap_Normal_822_3",
      "StepEnterScenarioGroupId": 0,
      "StepOpenConditionType": [
        4
      ],
      "StepOpenConditionParameter": [
        "82221131"
      ],
      "MapGoalLocalize": "UI_CONQUESTLOBBY_GOAL_STEP4",
      "StepGoalLocalize": "UI_CONQUESTLOBBY_GOAL_STEP3",
      "StepNameLocalize": "Stepname_EVENT_822_Normal_Step3",
      "ConquestMapBG": "Conquest_Back_02_Normal_Outer",
      "CameraSettingId": 82203
    },
    {
      "EventContentId": 50822,
      "DevName": "최종장방주_메인스토리",
      "MapDifficulty": 1,
      "StepIndex": 3,
      "ConquestMap": "ConquestMap_Normal_822_4",
      "StepEnterScenarioGroupId": 0,
      "StepOpenConditionType": [
        4
      ],
      "StepOpenConditionParameter": [
        "82231131"
      ],
      "MapGoalLocalize": "UI_CONQUESTLOBBY_GOAL_STEP4",
      "StepGoalLocalize": "UI_CONQUESTLOBBY_GOAL_STEP4",
      "StepNameLocalize": "Stepname_EVENT_822_Normal_Step4",
      "ConquestMapBG": "Conquest_Back_02_Normal_Inner",
      "CameraSettingId": 82204
    },
    {
      "EventContentId": 50822,
      "DevName": "최종장방주_메인스토리",
      "MapDifficulty": 3,
      "StepIndex": 0,
      "ConquestMap": "ConquestMap_Challenge_822",
      "StepEnterScenarioGroupId": 0,
      "StepOpenConditionType": [
        1
      ],
      "StepOpenConditionParameter": [
        "0"
      ],
      "MapGoalLocalize": "UI_CONQUESTLOBBY_GOAL_CHALLENGE",
      "StepGoalLocalize": "UI_CONQUESTLOBBY_GOAL_CHALLENGE",
      "StepNameLocalize": "Stepname_EVENT_822_Challenge_Step0",
      "ConquestMapBG": "Conquest_Back_02_Normal_Inner",
      "CameraSettingId": 82211
    }
  ]
}