{
  "DataList": [
    {
      "Id": 1,
      "FreeRecruitPeriodFrom": "2022-01-26 04:00:00",
      "FreeRecruitPeriodTo": "2022-02-09 03:59:59",
      "FreeRecruitType": 1,
      "FreeRecruitDecorationImagePath": "",
      "ShopRecruitId": [
        50121,
        50122,
        50123,
        50124
      ]
    },
    {
      "Id": 2,
      "FreeRecruitPeriodFrom": "2022-07-25 11:00:00",
      "FreeRecruitPeriodTo": "2022-08-03 11:00:00",
      "FreeRecruitType": 1,
      "FreeRecruitDecorationImagePath": "",
      "ShopRecruitId": [
        50192,
        50193,
        50194
      ]
    },
    {
      "Id": 3,
      "FreeRecruitPeriodFrom": "2023-01-31 11:00:00",
      "FreeRecruitPeriodTo": "2023-02-10 03:59:59",
      "FreeRecruitType": 1,
      "FreeRecruitDecorationImagePath": "",
      "ShopRecruitId": [
        50292,
        50293,
        50294
      ]
    },
    {
      "Id": 4,
      "FreeRecruitPeriodFrom": "2023-07-24 11:00:00",
      "FreeRecruitPeriodTo": "2023-08-02 10:59:59",
      "FreeRecruitType": 1,
      "FreeRecruitDecorationImagePath": "",
      "ShopRecruitId": [
        50383,
        50384,
        50385
      ]
    },
    {
      "Id": 5,
      "FreeRecruitPeriodFrom": "2024-01-24 11:00:00",
      "FreeRecruitPeriodTo": "2024-01-31 10:59:59",
      "FreeRecruitType": 1,
      "FreeRecruitDecorationImagePath": "",
      "ShopRecruitId": [
        50490,
        50491,
        50492,
        50493
      ]
    }
  ]
}